{
    "coinPairs": [
        {
            "pair": "BTCUSDT",
            "name": "BTC",
            "icon": "https://icons.iconarchive.com/icons/cjdowner/cryptocurrency-flat/1024/Bitcoin-BTC-icon.png",
            "colorHex": "fcba03"
        },
        {
            "pair": "BNBUSDT",
            "name": "BNB",
            "icon": "https://iconape.com/wp-content/png_logo_vector/binance-coin-bnb-logo.png",
            "colorHex": "fcf003"
        },
        {
            "pair": "ETHUSDT",
            "name": "ETH",
            "icon": "https://upload.wikimedia.org/wikipedia/commons/thumb/6/6f/Ethereum-icon-purple.svg/1200px-Ethereum-icon-purple.svg.png",
            "colorHex": "d7d9d7"
        },
        {
            "pair": "FIOUSDT",
            "pair": "FIO",
            "colorHex": "89cde8"
        },
        {
            "pair": "SFPUSDT",
            "pair": "SFP",
            "colorHex": "89cde8"
        },
        {
            "pair": "1INCHUSDT",
            "pair": "1INCH",
            "colorHex": "ffffff"
        }
    ]
}
